nonebot_plugin_binsearch/__init__.py
nonebot_plugin_binsearch/api.py
nonebot_plugin_binsearch/assets/american_express.svg
nonebot_plugin_binsearch/assets/bg_1.png
nonebot_plugin_binsearch/assets/bg_2.png
nonebot_plugin_binsearch/assets/jcb.svg
nonebot_plugin_binsearch/assets/mastercard.svg
nonebot_plugin_binsearch/assets/unionpay.svg
nonebot_plugin_binsearch/assets/visa.svg
nonebot_plugin_binsearch/config.py
nonebot_plugin_binsearch/fonts/STHUPO.TTF
nonebot_plugin_binsearch/image.py
nonebot_plugin_binsearch/main_bin.py
nonebot_plugin_binsearch/refused_bin.py
nonebot_plugin_binsearch/utils.py
nonebot_plugin_binsearch-3.3.0.dist-info/METADATA
nonebot_plugin_binsearch-3.3.0.dist-info/WHEEL
nonebot_plugin_binsearch-3.3.0.dist-info/licenses/LICENSE
nonebot_plugin_binsearch-3.3.0.dist-info/RECORD
