Metadata-Version: 2.4
Name: nonebot-plugin-binsearch
Version: 3.3.0
Summary: 一个Nonebot2插件用于查询信用卡的卡组织，卡等级，卡类型，发卡国等
License: GPL-3.0
License-File: LICENSE
Keywords: nonebot2,BankCard,binsearch
Author: Maizi
Author-email: maizicncn@gmail.com
Requires-Python: >=3.8,<4.0
Classifier: License :: OSI Approved :: GNU General Public License v3 (GPLv3)
Classifier: Programming Language :: Python :: 3
Classifier: Programming Language :: Python :: 3.8
Classifier: Programming Language :: Python :: 3.9
Classifier: Programming Language :: Python :: 3.10
Classifier: Programming Language :: Python :: 3.11
Classifier: Programming Language :: Python :: 3.12
Classifier: Programming Language :: Python :: 3.13
Classifier: Programming Language :: Python :: 3.14
Requires-Dist: cairosvg (>=2.0.0,<3.0.0)
Requires-Dist: httpx (>=0.26.0)
Requires-Dist: nonebot-adapter-onebot (>=2.0.0,<3.0.0)
Requires-Dist: nonebot2 (>=2.2.1,<3.0.0)
Requires-Dist: pillow (>=9.0.0,<11.0.0)
Project-URL: Documentation, https://github.com/bankcarddev/nonebot-plugin-binsearch#readme
Project-URL: Homepage, https://github.com/bankcarddev/nonebot-plugin-binsearch
Project-URL: Repository, https://github.com/bankcarddev/nonebot-plugin-binsearch
